utilidades/__init__.py
utilidades/utilidades.py
utilidades_11-1.1.data/scripts/utilidades.py
utilidades_11-1.1.data/scripts/uts.py
uts/__init__.py
uts/uts.py
utilidades_11-1.1.dist-info/LICENSE
utilidades_11-1.1.dist-info/METADATA
utilidades_11-1.1.dist-info/WHEEL
utilidades_11-1.1.dist-info/top_level.txt
utilidades_11-1.1.dist-info/RECORD
